demo/manage.py
demo/demo/__init__.py
demo/demo/asgi.py
demo/demo/settings.py
demo/demo/urls.py
demo/demo/wsgi.py
demo/polls/__init__.py
demo/polls/admin.py
demo/polls/apps.py
demo/polls/models.py
demo/polls/urls.py
demo/polls/views.py
demo/polls/migrations/0001_initial.py
demo/polls/migrations/0002_poll_file.py
demo/polls/migrations/0003_rename_subdomain_tenant_prefix.py
demo/polls/migrations/__init__.py
simple_tenants/__init__.py
simple_tenants/admin.py
simple_tenants/conf.py
simple_tenants/errors.py
simple_tenants/managers.py
simple_tenants/middleware.py
simple_tenants/models.py
simple_tenants/utils.py
django_simple_tenants-0.4.0.dist-info/METADATA
django_simple_tenants-0.4.0.dist-info/WHEEL
django_simple_tenants-0.4.0.dist-info/licenses/LICENSE
django_simple_tenants-0.4.0.dist-info/RECORD
