Metadata-Version: 2.1
Name: django-simple-tenants
Version: 0.4.0
Project-URL: Documentation, https://Tobi-De.github.io/django-simple-tenants/
Project-URL: Source, https://github.com/Tobi-De/django-simple-tenants
Author-email: django-simple-tenants <tobidegnon@proton.me>
License-File: LICENSE
Classifier: Programming Language :: Python :: 3 :: Only
Requires-Python: >=3.8
Requires-Dist: django>=3
